setup.py
testPy/__init__.py
testPy.egg-info/PKG-INFO
testPy.egg-info/SOURCES.txt
testPy.egg-info/dependency_links.txt
testPy.egg-info/not-zip-safe
testPy.egg-info/top_level.txt