Metadata-Version: 1.0
Name: testPy
Version: 0.3
Summary: this a test for testPy
Home-page: http://www.wecash.net
Author: Joshua Tang
Author-email: txw@outlook.com
License: MIT
Platform: UNKNOWN
